[
  {
    "ContainingType": "AllFoodAPI.WebApi.Controllers.AddressController",
    "Method": "GetAllAddresses",
    "RelativePath": "api/address",
    "HttpMethod": "GET",
    "IsController": true,
    "Order": 0,
    "Parameters": [],
    "ReturnTypes": []
  },
  {
    "ContainingType": "AllFoodAPI.WebApi.Controllers.AddressController",
    "Method": "AddAddress",
    "RelativePath": "api/address/add",
    "HttpMethod": "POST",
    "IsController": true,
    "Order": 0,
    "Parameters": [
      {
        "Name": "address",
        "Type": "AllFoodAPI.Core.DTOs.AddressDTO",
        "IsRequired": true
      }
    ],
    "ReturnTypes": []
  },
  {
    "ContainingType": "AllFoodAPI.WebApi.Controllers.AddressController",
    "Method": "GetAddressById",
    "RelativePath": "api/address/addressId={id}",
    "HttpMethod": "GET",
    "IsController": true,
    "Order": 0,
    "Parameters": [
      {
        "Name": "id",
        "Type": "System.Int32",
        "IsRequired": true
      }
    ],
    "ReturnTypes": [
      {
        "Type": "AllFoodAPI.Core.DTOs.AddressDTO",
        "MediaTypes": [
          "text/plain",
          "application/json",
          "text/json"
        ],
        "StatusCode": 200
      }
    ]
  },
  {
    "ContainingType": "AllFoodAPI.WebApi.Controllers.AddressController",
    "Method": "DeleteAddress",
    "RelativePath": "api/address/remove/{id}",
    "HttpMethod": "DELETE",
    "IsController": true,
    "Order": 0,
    "Parameters": [
      {
        "Name": "id",
        "Type": "System.Int32",
        "IsRequired": true
      }
    ],
    "ReturnTypes": []
  },
  {
    "ContainingType": "AllFoodAPI.WebApi.Controllers.AddressController",
    "Method": "UpdateAddress",
    "RelativePath": "api/address/update/{id}",
    "HttpMethod": "PUT",
    "IsController": true,
    "Order": 0,
    "Parameters": [
      {
        "Name": "address",
        "Type": "System.String",
        "IsRequired": true
      },
      {
        "Name": "id",
        "Type": "System.Int32",
        "IsRequired": true
      }
    ],
    "ReturnTypes": []
  },
  {
    "ContainingType": "AllFoodAPI.WebApi.Controllers.AddressController",
    "Method": "GetAddressByUserId",
    "RelativePath": "api/address/userId={id}",
    "HttpMethod": "GET",
    "IsController": true,
    "Order": 0,
    "Parameters": [
      {
        "Name": "id",
        "Type": "System.Int32",
        "IsRequired": true
      }
    ],
    "ReturnTypes": [
      {
        "Type": "AllFoodAPI.Core.DTOs.AddressDTO",
        "MediaTypes": [
          "text/plain",
          "application/json",
          "text/json"
        ],
        "StatusCode": 200
      }
    ]
  },
  {
    "ContainingType": "AllFoodAPI.WebApi.Controllers.CartController",
    "Method": "AddCart",
    "RelativePath": "api/cart/add",
    "HttpMethod": "POST",
    "IsController": true,
    "Order": 0,
    "Parameters": [
      {
        "Name": "cart",
        "Type": "AllFoodAPI.WebApi.Models.Cart.AddCartModel",
        "IsRequired": true
      }
    ],
    "ReturnTypes": []
  },
  {
    "ContainingType": "AllFoodAPI.WebApi.Controllers.CartController",
    "Method": "GetCartByUserId",
    "RelativePath": "api/cart/userId={userId}",
    "HttpMethod": "GET",
    "IsController": true,
    "Order": 0,
    "Parameters": [
      {
        "Name": "userId",
        "Type": "System.Int32",
        "IsRequired": true
      }
    ],
    "ReturnTypes": []
  },
  {
    "ContainingType": "AllFoodAPI.WebApi.Controllers.CartDetailController",
    "Method": "AddCartDetail",
    "RelativePath": "api/cartdetail/add",
    "HttpMethod": "POST",
    "IsController": true,
    "Order": 0,
    "Parameters": [
      {
        "Name": "cartDetailDTO",
        "Type": "AllFoodAPI.WebApi.Models.Cart.AddCartDetailModel",
        "IsRequired": true
      }
    ],
    "ReturnTypes": []
  },
  {
    "ContainingType": "AllFoodAPI.WebApi.Controllers.CartDetailController",
    "Method": "DeleteCartDetail",
    "RelativePath": "api/cartdetail/remove/productId={productId}/cartId={cartId}",
    "HttpMethod": "DELETE",
    "IsController": true,
    "Order": 0,
    "Parameters": [
      {
        "Name": "productId",
        "Type": "System.Int32",
        "IsRequired": true
      },
      {
        "Name": "cartId",
        "Type": "System.Int32",
        "IsRequired": true
      }
    ],
    "ReturnTypes": []
  },
  {
    "ContainingType": "AllFoodAPI.WebApi.Controllers.CartDetailController",
    "Method": "UpdateCartDetail",
    "RelativePath": "api/cartdetail/updatequantity={quantity}/productId={productId}/cartId={cartId}",
    "HttpMethod": "PUT",
    "IsController": true,
    "Order": 0,
    "Parameters": [
      {
        "Name": "quantity",
        "Type": "System.Int32",
        "IsRequired": true
      },
      {
        "Name": "productId",
        "Type": "System.Int32",
        "IsRequired": true
      },
      {
        "Name": "cartId",
        "Type": "System.Int32",
        "IsRequired": true
      }
    ],
    "ReturnTypes": []
  },
  {
    "ContainingType": "AllFoodAPI.WebApi.Controllers.CategoryController",
    "Method": "GetAllCategories",
    "RelativePath": "api/category",
    "HttpMethod": "GET",
    "IsController": true,
    "Order": 0,
    "Parameters": [],
    "ReturnTypes": []
  },
  {
    "ContainingType": "AllFoodAPI.WebApi.Controllers.CategoryController",
    "Method": "GetCategoryById",
    "RelativePath": "api/category/{id}",
    "HttpMethod": "GET",
    "IsController": true,
    "Order": 0,
    "Parameters": [
      {
        "Name": "id",
        "Type": "System.Int32",
        "IsRequired": true
      }
    ],
    "ReturnTypes": [
      {
        "Type": "AllFoodAPI.Core.DTOs.CategoryDTO",
        "MediaTypes": [
          "text/plain",
          "application/json",
          "text/json"
        ],
        "StatusCode": 200
      }
    ]
  },
  {
    "ContainingType": "AllFoodAPI.WebApi.Controllers.CategoryController",
    "Method": "DeleteCategory",
    "RelativePath": "api/category/{id}",
    "HttpMethod": "DELETE",
    "IsController": true,
    "Order": 0,
    "Parameters": [
      {
        "Name": "id",
        "Type": "System.Int32",
        "IsRequired": true
      }
    ],
    "ReturnTypes": []
  },
  {
    "ContainingType": "AllFoodAPI.WebApi.Controllers.CategoryController",
    "Method": "AddCategory",
    "RelativePath": "api/category/add",
    "HttpMethod": "POST",
    "IsController": true,
    "Order": 0,
    "Parameters": [
      {
        "Name": "categoryDTO",
        "Type": "AllFoodAPI.Core.DTOs.CategoryDTO",
        "IsRequired": true
      }
    ],
    "ReturnTypes": []
  },
  {
    "ContainingType": "AllFoodAPI.WebApi.Controllers.CategoryController",
    "Method": "GetCategoriesByShopId",
    "RelativePath": "api/category/shopId={shopId}",
    "HttpMethod": "GET",
    "IsController": true,
    "Order": 0,
    "Parameters": [
      {
        "Name": "shopId",
        "Type": "System.Int32",
        "IsRequired": true
      }
    ],
    "ReturnTypes": []
  },
  {
    "ContainingType": "AllFoodAPI.WebApi.Controllers.CategoryController",
    "Method": "UpdateCategory",
    "RelativePath": "api/category/update",
    "HttpMethod": "PUT",
    "IsController": true,
    "Order": 0,
    "Parameters": [
      {
        "Name": "categoryDTO",
        "Type": "AllFoodAPI.Core.DTOs.CategoryDTO",
        "IsRequired": true
      }
    ],
    "ReturnTypes": []
  },
  {
    "ContainingType": "AllFoodAPI.WebApi.Controllers.ImageController",
    "Method": "GetAllImages",
    "RelativePath": "api/image",
    "HttpMethod": "GET",
    "IsController": true,
    "Order": 0,
    "Parameters": [],
    "ReturnTypes": []
  },
  {
    "ContainingType": "AllFoodAPI.WebApi.Controllers.ImageController",
    "Method": "DeleteImage",
    "RelativePath": "api/image/{id}",
    "HttpMethod": "DELETE",
    "IsController": true,
    "Order": 0,
    "Parameters": [
      {
        "Name": "id",
        "Type": "System.Int32",
        "IsRequired": true
      }
    ],
    "ReturnTypes": []
  },
  {
    "ContainingType": "AllFoodAPI.WebApi.Controllers.ImageController",
    "Method": "AddImage",
    "RelativePath": "api/image/add",
    "HttpMethod": "POST",
    "IsController": true,
    "Order": 0,
    "Parameters": [
      {
        "Name": "image",
        "Type": "AllFoodAPI.Core.DTOs.ImageDTO",
        "IsRequired": true
      }
    ],
    "ReturnTypes": []
  },
  {
    "ContainingType": "AllFoodAPI.WebApi.Controllers.ImageController",
    "Method": "GetImageById",
    "RelativePath": "api/image/imageId={id}",
    "HttpMethod": "GET",
    "IsController": true,
    "Order": 0,
    "Parameters": [
      {
        "Name": "id",
        "Type": "System.Int32",
        "IsRequired": true
      }
    ],
    "ReturnTypes": [
      {
        "Type": "AllFoodAPI.Core.Entities.Image",
        "MediaTypes": [
          "text/plain",
          "application/json",
          "text/json"
        ],
        "StatusCode": 200
      }
    ]
  },
  {
    "ContainingType": "AllFoodAPI.WebApi.Controllers.ImageController",
    "Method": "GetImageByProductId",
    "RelativePath": "api/image/productId={id}",
    "HttpMethod": "GET",
    "IsController": true,
    "Order": 0,
    "Parameters": [
      {
        "Name": "productId",
        "Type": "System.Int32",
        "IsRequired": false
      },
      {
        "Name": "id",
        "Type": "",
        "IsRequired": true
      }
    ],
    "ReturnTypes": [
      {
        "Type": "AllFoodAPI.Core.Entities.Image",
        "MediaTypes": [
          "text/plain",
          "application/json",
          "text/json"
        ],
        "StatusCode": 200
      }
    ]
  },
  {
    "ContainingType": "AllFoodAPI.WebApi.Controllers.ImageController",
    "Method": "UpdateImage",
    "RelativePath": "api/image/update/{id}",
    "HttpMethod": "PUT",
    "IsController": true,
    "Order": 0,
    "Parameters": [
      {
        "Name": "imageURL",
        "Type": "System.String",
        "IsRequired": true
      },
      {
        "Name": "id",
        "Type": "System.Int32",
        "IsRequired": true
      }
    ],
    "ReturnTypes": []
  },
  {
    "ContainingType": "AllFoodAPI.WebApi.Controllers.ProductController",
    "Method": "GetAllProducts",
    "RelativePath": "api/product",
    "HttpMethod": "GET",
    "IsController": true,
    "Order": 0,
    "Parameters": [],
    "ReturnTypes": []
  },
  {
    "ContainingType": "AllFoodAPI.WebApi.Controllers.ProductController",
    "Method": "AddCategory",
    "RelativePath": "api/product/add",
    "HttpMethod": "POST",
    "IsController": true,
    "Order": 0,
    "Parameters": [
      {
        "Name": "product",
        "Type": "AllFoodAPI.WebApi.Models.Product.AddProductModel",
        "IsRequired": true
      }
    ],
    "ReturnTypes": []
  },
  {
    "ContainingType": "AllFoodAPI.WebApi.Controllers.ProductController",
    "Method": "GetProductByCategoryId",
    "RelativePath": "api/product/categoryId={categoryId}",
    "HttpMethod": "GET",
    "IsController": true,
    "Order": 0,
    "Parameters": [
      {
        "Name": "categoryId",
        "Type": "System.Int32",
        "IsRequired": true
      }
    ],
    "ReturnTypes": [
      {
        "Type": "AllFoodAPI.Core.DTOs.ProductDTO",
        "MediaTypes": [
          "text/plain",
          "application/json",
          "text/json"
        ],
        "StatusCode": 200
      }
    ]
  },
  {
    "ContainingType": "AllFoodAPI.WebApi.Controllers.ProductController",
    "Method": "GetNHighestProducts",
    "RelativePath": "api/product/Get{n}HighestProducts",
    "HttpMethod": "GET",
    "IsController": true,
    "Order": 0,
    "Parameters": [
      {
        "Name": "n",
        "Type": "System.Int32",
        "IsRequired": true
      }
    ],
    "ReturnTypes": []
  },
  {
    "ContainingType": "AllFoodAPI.WebApi.Controllers.ProductController",
    "Method": "GetProductByName",
    "RelativePath": "api/product/name={name}",
    "HttpMethod": "GET",
    "IsController": true,
    "Order": 0,
    "Parameters": [
      {
        "Name": "name",
        "Type": "System.String",
        "IsRequired": true
      }
    ],
    "ReturnTypes": [
      {
        "Type": "AllFoodAPI.WebApi.Models.Product.ResponseSearch",
        "MediaTypes": [
          "text/plain",
          "application/json",
          "text/json"
        ],
        "StatusCode": 200
      }
    ]
  },
  {
    "ContainingType": "AllFoodAPI.WebApi.Controllers.ProductController",
    "Method": "GetProductById",
    "RelativePath": "api/product/productId={id}",
    "HttpMethod": "GET",
    "IsController": true,
    "Order": 0,
    "Parameters": [
      {
        "Name": "id",
        "Type": "System.Int32",
        "IsRequired": true
      }
    ],
    "ReturnTypes": [
      {
        "Type": "AllFoodAPI.Core.DTOs.ProductDTO",
        "MediaTypes": [
          "text/plain",
          "application/json",
          "text/json"
        ],
        "StatusCode": 200
      }
    ]
  },
  {
    "ContainingType": "AllFoodAPI.WebApi.Controllers.ProductController",
    "Method": "DeleteProduct",
    "RelativePath": "api/product/remove/{id}",
    "HttpMethod": "DELETE",
    "IsController": true,
    "Order": 0,
    "Parameters": [
      {
        "Name": "id",
        "Type": "System.Int32",
        "IsRequired": true
      }
    ],
    "ReturnTypes": []
  },
  {
    "ContainingType": "AllFoodAPI.WebApi.Controllers.ProductController",
    "Method": "UpdateCategory",
    "RelativePath": "api/product/update/shopid={shopId}/productId={productId}",
    "HttpMethod": "PUT",
    "IsController": true,
    "Order": 0,
    "Parameters": [
      {
        "Name": "product",
        "Type": "AllFoodAPI.WebApi.Models.Product.UpdateProductModel",
        "IsRequired": true
      },
      {
        "Name": "shopId",
        "Type": "System.Int32",
        "IsRequired": true
      },
      {
        "Name": "productId",
        "Type": "System.Int32",
        "IsRequired": true
      }
    ],
    "ReturnTypes": []
  },
  {
    "ContainingType": "AllFoodAPI.WebApi.Controllers.ReportController",
    "Method": "GetAllReports",
    "RelativePath": "api/report",
    "HttpMethod": "GET",
    "IsController": true,
    "Order": 0,
    "Parameters": [],
    "ReturnTypes": []
  },
  {
    "ContainingType": "AllFoodAPI.WebApi.Controllers.ReportController",
    "Method": "GetReportById",
    "RelativePath": "api/report/{id}",
    "HttpMethod": "GET",
    "IsController": true,
    "Order": 0,
    "Parameters": [
      {
        "Name": "id",
        "Type": "System.Int32",
        "IsRequired": true
      }
    ],
    "ReturnTypes": [
      {
        "Type": "AllFoodAPI.Core.DTOs.ReportDTO",
        "MediaTypes": [
          "text/plain",
          "application/json",
          "text/json"
        ],
        "StatusCode": 200
      }
    ]
  },
  {
    "ContainingType": "AllFoodAPI.WebApi.Controllers.ReportController",
    "Method": "AddReport",
    "RelativePath": "api/report/add",
    "HttpMethod": "POST",
    "IsController": true,
    "Order": 0,
    "Parameters": [
      {
        "Name": "report",
        "Type": "AllFoodAPI.WebApi.Models.Report.AddReportModel",
        "IsRequired": true
      }
    ],
    "ReturnTypes": []
  },
  {
    "ContainingType": "AllFoodAPI.WebApi.Controllers.ReportController",
    "Method": "DeleteReport",
    "RelativePath": "api/report/remove/{id}",
    "HttpMethod": "DELETE",
    "IsController": true,
    "Order": 0,
    "Parameters": [
      {
        "Name": "id",
        "Type": "System.Int32",
        "IsRequired": true
      }
    ],
    "ReturnTypes": []
  },
  {
    "ContainingType": "AllFoodAPI.WebApi.Controllers.ReportController",
    "Method": "UpdateReport",
    "RelativePath": "api/report/update/{id}",
    "HttpMethod": "PUT",
    "IsController": true,
    "Order": 0,
    "Parameters": [
      {
        "Name": "reason",
        "Type": "System.String",
        "IsRequired": true
      },
      {
        "Name": "id",
        "Type": "System.Int32",
        "IsRequired": true
      }
    ],
    "ReturnTypes": []
  },
  {
    "ContainingType": "AllFoodAPI.WebApi.Controllers.ReviewController",
    "Method": "GetAllReviews",
    "RelativePath": "api/review",
    "HttpMethod": "GET",
    "IsController": true,
    "Order": 0,
    "Parameters": [],
    "ReturnTypes": []
  },
  {
    "ContainingType": "AllFoodAPI.WebApi.Controllers.ReviewController",
    "Method": "AddReview",
    "RelativePath": "api/review/add",
    "HttpMethod": "POST",
    "IsController": true,
    "Order": 0,
    "Parameters": [
      {
        "Name": "review",
        "Type": "AllFoodAPI.WebApi.Models.Review.AddReviewModel",
        "IsRequired": true
      }
    ],
    "ReturnTypes": []
  },
  {
    "ContainingType": "AllFoodAPI.WebApi.Controllers.ReviewController",
    "Method": "GetReviewByProductId",
    "RelativePath": "api/review/productId={productId}",
    "HttpMethod": "GET",
    "IsController": true,
    "Order": 0,
    "Parameters": [
      {
        "Name": "productId",
        "Type": "System.Int32",
        "IsRequired": true
      }
    ],
    "ReturnTypes": [
      {
        "Type": "AllFoodAPI.Core.DTOs.ReviewDTO",
        "MediaTypes": [
          "text/plain",
          "application/json",
          "text/json"
        ],
        "StatusCode": 200
      }
    ]
  },
  {
    "ContainingType": "AllFoodAPI.WebApi.Controllers.ReviewController",
    "Method": "DeleteReview",
    "RelativePath": "api/review/remove/{id}",
    "HttpMethod": "DELETE",
    "IsController": true,
    "Order": 0,
    "Parameters": [
      {
        "Name": "id",
        "Type": "System.Int32",
        "IsRequired": true
      }
    ],
    "ReturnTypes": []
  },
  {
    "ContainingType": "AllFoodAPI.WebApi.Controllers.ReviewController",
    "Method": "GetReviewById",
    "RelativePath": "api/review/reviewId={id}",
    "HttpMethod": "GET",
    "IsController": true,
    "Order": 0,
    "Parameters": [
      {
        "Name": "id",
        "Type": "System.Int32",
        "IsRequired": true
      }
    ],
    "ReturnTypes": [
      {
        "Type": "AllFoodAPI.Core.DTOs.ReviewDTO",
        "MediaTypes": [
          "text/plain",
          "application/json",
          "text/json"
        ],
        "StatusCode": 200
      }
    ]
  },
  {
    "ContainingType": "AllFoodAPI.WebApi.Controllers.ReviewController",
    "Method": "UpdateReview",
    "RelativePath": "api/review/update/{id}",
    "HttpMethod": "PUT",
    "IsController": true,
    "Order": 0,
    "Parameters": [
      {
        "Name": "review",
        "Type": "AllFoodAPI.WebApi.Models.Review.UpdateReviewModel",
        "IsRequired": true
      },
      {
        "Name": "id",
        "Type": "System.Int32",
        "IsRequired": true
      }
    ],
    "ReturnTypes": []
  },
  {
    "ContainingType": "AllFoodAPI.WebApi.Controllers.ShopController",
    "Method": "GetAllShops",
    "RelativePath": "api/shop",
    "HttpMethod": "GET",
    "IsController": true,
    "Order": 0,
    "Parameters": [],
    "ReturnTypes": []
  },
  {
    "ContainingType": "AllFoodAPI.WebApi.Controllers.ShopController",
    "Method": "AddShop",
    "RelativePath": "api/shop/add",
    "HttpMethod": "POST",
    "IsController": true,
    "Order": 0,
    "Parameters": [
      {
        "Name": "shop",
        "Type": "AllFoodAPI.WebApi.Models.Shop.AddShopModel",
        "IsRequired": true
      }
    ],
    "ReturnTypes": []
  },
  {
    "ContainingType": "AllFoodAPI.WebApi.Controllers.ShopController",
    "Method": "GetNHighestShops",
    "RelativePath": "api/shop/Get{n}HighestShops",
    "HttpMethod": "GET",
    "IsController": true,
    "Order": 0,
    "Parameters": [
      {
        "Name": "n",
        "Type": "System.Int32",
        "IsRequired": true
      }
    ],
    "ReturnTypes": []
  },
  {
    "ContainingType": "AllFoodAPI.WebApi.Controllers.ShopController",
    "Method": "DeleteShop",
    "RelativePath": "api/shop/remove/{shopId}",
    "HttpMethod": "DELETE",
    "IsController": true,
    "Order": 0,
    "Parameters": [
      {
        "Name": "shopId",
        "Type": "System.Int32",
        "IsRequired": true
      }
    ],
    "ReturnTypes": []
  },
  {
    "ContainingType": "AllFoodAPI.WebApi.Controllers.ShopController",
    "Method": "GetShopById",
    "RelativePath": "api/shop/shopId={shopId}",
    "HttpMethod": "GET",
    "IsController": true,
    "Order": 0,
    "Parameters": [
      {
        "Name": "shopId",
        "Type": "System.Int32",
        "IsRequired": true
      }
    ],
    "ReturnTypes": [
      {
        "Type": "AllFoodAPI.Core.DTOs.AddressDTO",
        "MediaTypes": [
          "text/plain",
          "application/json",
          "text/json"
        ],
        "StatusCode": 200
      }
    ]
  },
  {
    "ContainingType": "AllFoodAPI.WebApi.Controllers.ShopController",
    "Method": "UpdateShop",
    "RelativePath": "api/shop/update/{id}",
    "HttpMethod": "PUT",
    "IsController": true,
    "Order": 0,
    "Parameters": [
      {
        "Name": "shop",
        "Type": "AllFoodAPI.WebApi.Models.Shop.UpdateShopModel",
        "IsRequired": true
      },
      {
        "Name": "id",
        "Type": "System.Int32",
        "IsRequired": true
      }
    ],
    "ReturnTypes": []
  },
  {
    "ContainingType": "AllFoodAPI.WebApi.Controllers.ShopController",
    "Method": "GetShopByUserId",
    "RelativePath": "api/shop/userId={userId}",
    "HttpMethod": "GET",
    "IsController": true,
    "Order": 0,
    "Parameters": [
      {
        "Name": "userId",
        "Type": "System.Int32",
        "IsRequired": true
      }
    ],
    "ReturnTypes": [
      {
        "Type": "AllFoodAPI.Core.DTOs.AddressDTO",
        "MediaTypes": [
          "text/plain",
          "application/json",
          "text/json"
        ],
        "StatusCode": 200
      }
    ]
  },
  {
    "ContainingType": "AllFoodAPI.WebApi.Controllers.UserController",
    "Method": "GetAllUsers",
    "RelativePath": "api/user",
    "HttpMethod": "GET",
    "IsController": true,
    "Order": 0,
    "Parameters": [],
    "ReturnTypes": []
  },
  {
    "ContainingType": "AllFoodAPI.WebApi.Controllers.UserController",
    "Method": "GetUserById",
    "RelativePath": "api/user/{id}",
    "HttpMethod": "GET",
    "IsController": true,
    "Order": 0,
    "Parameters": [
      {
        "Name": "id",
        "Type": "System.Int32",
        "IsRequired": true
      }
    ],
    "ReturnTypes": [
      {
        "Type": "AllFoodAPI.Core.DTOs.UserDTO",
        "MediaTypes": [
          "text/plain",
          "application/json",
          "text/json"
        ],
        "StatusCode": 200
      }
    ]
  },
  {
    "ContainingType": "AllFoodAPI.WebApi.Controllers.UserController",
    "Method": "AddUser",
    "RelativePath": "api/user/add",
    "HttpMethod": "POST",
    "IsController": true,
    "Order": 0,
    "Parameters": [
      {
        "Name": "user",
        "Type": "AllFoodAPI.WebApi.Models.User.AddUserModel",
        "IsRequired": true
      }
    ],
    "ReturnTypes": []
  },
  {
    "ContainingType": "AllFoodAPI.WebApi.Controllers.UserController",
    "Method": "ChangePassword",
    "RelativePath": "api/user/changepassword/userId={id}",
    "HttpMethod": "PATCH",
    "IsController": true,
    "Order": 0,
    "Parameters": [
      {
        "Name": "model",
        "Type": "AllFoodAPI.WebApi.Models.User.ChangePasswordModel",
        "IsRequired": true
      },
      {
        "Name": "id",
        "Type": "System.Int32",
        "IsRequired": true
      }
    ],
    "ReturnTypes": []
  },
  {
    "ContainingType": "AllFoodAPI.WebApi.Controllers.UserController",
    "Method": "Login",
    "RelativePath": "api/user/login",
    "HttpMethod": "POST",
    "IsController": true,
    "Order": 0,
    "Parameters": [
      {
        "Name": "loginDTO",
        "Type": "AllFoodAPI.WebApi.Models.User.LoginModel",
        "IsRequired": true
      }
    ],
    "ReturnTypes": []
  },
  {
    "ContainingType": "AllFoodAPI.WebApi.Controllers.UserController",
    "Method": "DeleteUser",
    "RelativePath": "api/user/remove/{id}",
    "HttpMethod": "DELETE",
    "IsController": true,
    "Order": 0,
    "Parameters": [
      {
        "Name": "id",
        "Type": "System.Int32",
        "IsRequired": true
      }
    ],
    "ReturnTypes": []
  },
  {
    "ContainingType": "AllFoodAPI.WebApi.Controllers.UserController",
    "Method": "UpdateUser",
    "RelativePath": "api/user/update/{id}",
    "HttpMethod": "PUT",
    "IsController": true,
    "Order": 0,
    "Parameters": [
      {
        "Name": "userUpdate",
        "Type": "AllFoodAPI.WebApi.Models.User.UpdateUserModel",
        "IsRequired": true
      },
      {
        "Name": "id",
        "Type": "System.Int32",
        "IsRequired": true
      }
    ],
    "ReturnTypes": []
  },
  {
    "ContainingType": "AllFoodAPI.WebApi.Controllers.VoucherCotroller",
    "Method": "GetAllVouchers",
    "RelativePath": "api/voucher",
    "HttpMethod": "GET",
    "IsController": true,
    "Order": 0,
    "Parameters": [],
    "ReturnTypes": []
  },
  {
    "ContainingType": "AllFoodAPI.WebApi.Controllers.VoucherCotroller",
    "Method": "AddVoucher",
    "RelativePath": "api/voucher/add",
    "HttpMethod": "POST",
    "IsController": true,
    "Order": 0,
    "Parameters": [
      {
        "Name": "voucher",
        "Type": "AllFoodAPI.WebApi.Models.Voucher.AddVoucherModel",
        "IsRequired": true
      }
    ],
    "ReturnTypes": []
  },
  {
    "ContainingType": "AllFoodAPI.WebApi.Controllers.VoucherCotroller",
    "Method": "DeleteVoucher",
    "RelativePath": "api/voucher/remove/{id}",
    "HttpMethod": "DELETE",
    "IsController": true,
    "Order": 0,
    "Parameters": [
      {
        "Name": "id",
        "Type": "System.Int32",
        "IsRequired": true
      }
    ],
    "ReturnTypes": []
  },
  {
    "ContainingType": "AllFoodAPI.WebApi.Controllers.VoucherCotroller",
    "Method": "GetVoucherByShopId",
    "RelativePath": "api/voucher/shopId={id}",
    "HttpMethod": "GET",
    "IsController": true,
    "Order": 0,
    "Parameters": [
      {
        "Name": "shopId",
        "Type": "System.Int32",
        "IsRequired": false
      },
      {
        "Name": "id",
        "Type": "",
        "IsRequired": true
      }
    ],
    "ReturnTypes": [
      {
        "Type": "AllFoodAPI.Core.DTOs.VoucherDTO",
        "MediaTypes": [
          "text/plain",
          "application/json",
          "text/json"
        ],
        "StatusCode": 200
      }
    ]
  },
  {
    "ContainingType": "AllFoodAPI.WebApi.Controllers.VoucherCotroller",
    "Method": "UpdateVoucher",
    "RelativePath": "api/voucher/update/{id}",
    "HttpMethod": "PUT",
    "IsController": true,
    "Order": 0,
    "Parameters": [
      {
        "Name": "voucher",
        "Type": "AllFoodAPI.WebApi.Models.Voucher.UpdateVoucherModel",
        "IsRequired": true
      },
      {
        "Name": "id",
        "Type": "System.Int32",
        "IsRequired": true
      }
    ],
    "ReturnTypes": []
  },
  {
    "ContainingType": "AllFoodAPI.WebApi.Controllers.VoucherCotroller",
    "Method": "GetVoucherById",
    "RelativePath": "api/voucher/voucherId={id}",
    "HttpMethod": "GET",
    "IsController": true,
    "Order": 0,
    "Parameters": [
      {
        "Name": "id",
        "Type": "System.Int32",
        "IsRequired": true
      }
    ],
    "ReturnTypes": [
      {
        "Type": "AllFoodAPI.Core.DTOs.VoucherDTO",
        "MediaTypes": [
          "text/plain",
          "application/json",
          "text/json"
        ],
        "StatusCode": 200
      }
    ]
  }
]